pyrama/__init__.py
pyrama/config.py
pyrama/data/pref_general.data
pyrama/data/pref_glycine.data
pyrama/data/pref_preproline.data
pyrama/data/pref_proline.data
pyrama-2.0.2.data/scripts/pyrama
pyrama-2.0.2.dist-info/METADATA
pyrama-2.0.2.dist-info/WHEEL
pyrama-2.0.2.dist-info/top_level.txt
pyrama-2.0.2.dist-info/RECORD
